django_unicorn/__init__.py
django_unicorn/cacher.py
django_unicorn/call_method_parser.py
django_unicorn/db.py
django_unicorn/decorators.py
django_unicorn/errors.py
django_unicorn/serializer.py
django_unicorn/settings.py
django_unicorn/typer.py
django_unicorn/typing.py
django_unicorn/unicorn-ascii.txt
django_unicorn/urls.py
django_unicorn/utils.py
django_unicorn/components/__init__.py
django_unicorn/components/fields.py
django_unicorn/components/mixins.py
django_unicorn/components/unicorn_template_response.py
django_unicorn/components/unicorn_view.py
django_unicorn/components/updaters.py
django_unicorn/management/commands/startunicorn.py
django_unicorn/static/unicorn/js/.babelrc.json
django_unicorn/static/unicorn/js/attribute.js
django_unicorn/static/unicorn/js/component.js
django_unicorn/static/unicorn/js/delayers.js
django_unicorn/static/unicorn/js/element.js
django_unicorn/static/unicorn/js/eventListeners.js
django_unicorn/static/unicorn/js/messageSender.js
django_unicorn/static/unicorn/js/morpher.js
django_unicorn/static/unicorn/js/store.js
django_unicorn/static/unicorn/js/unicorn.js
django_unicorn/static/unicorn/js/unicorn.min.js
django_unicorn/static/unicorn/js/utils.js
django_unicorn/static/unicorn/js/morphdom/2.6.1/morphdom-umd.min.js
django_unicorn/static/unicorn/js/morphdom/2.6.1/morphdom.js
django_unicorn/static/unicorn/js/morphers/alpine.js
django_unicorn/static/unicorn/js/morphers/morphdom.js
django_unicorn/templates/unicorn/errors.html
django_unicorn/templates/unicorn/scripts.html
django_unicorn/templatetags/__init__.py
django_unicorn/templatetags/unicorn.py
django_unicorn/views/__init__.py
django_unicorn/views/action.py
django_unicorn/views/message.py
django_unicorn/views/objects.py
django_unicorn/views/request.py
django_unicorn/views/response.py
django_unicorn/views/utils.py
django_unicorn/views/action_parsers/__init__.py
django_unicorn/views/action_parsers/call_method.py
django_unicorn/views/action_parsers/sync_input.py
django_unicorn-0.64.0.dist-info/METADATA
django_unicorn-0.64.0.dist-info/WHEEL
django_unicorn-0.64.0.dist-info/licenses/LICENSE
django_unicorn-0.64.0.dist-info/RECORD
