Metadata-Version: 2.4
Name: django-unicorn
Version: 0.64.0
Summary: A magical full-stack framework for Django.
Project-URL: Homepage, https://www.django-unicorn.com
Project-URL: Repository, https://github.com/adamghill/django-unicorn/
Project-URL: Documentation, https://www.django-unicorn.com/docs/
Project-URL: Funding, https://github.com/sponsors/adamghill
Author-email: Adam Hill <unicorn@adamghill.com>
License: MIT
License-File: LICENSE
Keywords: django,fullstack,javascript,python
Classifier: Framework :: Django
Classifier: License :: OSI Approved :: MIT License
Classifier: Operating System :: OS Independent
Classifier: Programming Language :: Python :: 3
Requires-Python: >=3.10
Requires-Dist: cachetools>=4.1.1
Requires-Dist: decorator>=4.4.2
Requires-Dist: django>=2.2
Requires-Dist: lxml
Requires-Dist: orjson>=3.6.0
Requires-Dist: shortuuid>=1.0.1
Provides-Extra: docs
Requires-Dist: furo; extra == 'docs'
Requires-Dist: linkify-it-py; extra == 'docs'
Requires-Dist: myst-parser; extra == 'docs'
Requires-Dist: rst2pdf; extra == 'docs'
Requires-Dist: sphinx; extra == 'docs'
Requires-Dist: sphinx-autoapi; extra == 'docs'
Requires-Dist: sphinx-autobuild; extra == 'docs'
Requires-Dist: sphinx-copybutton; extra == 'docs'
Requires-Dist: sphinx-design; extra == 'docs'
Requires-Dist: sphinxext-opengraph; extra == 'docs'
Requires-Dist: toml; extra == 'docs'
Provides-Extra: minify
Requires-Dist: htmlmin; extra == 'minify'
